{
  "last_run": "2026-04-18T13:04Z",
  "comments": {
    "1213": "done",
    "1335": "done",
    "981": "done",
    "413": "done",
    "670": "done",
    "654": "done",
    "336": "done",
    "368": "done",
    "820": "done",
    "1313": "done",
    "412": "done",
    "402": "done",
    "539": "done",
    "618": "done",
    "1039": "done",
    "529": "done",
    "1442": "done",
    "1268": "done",
    "1240": "done",
    "807": "done",
    "1180": "done",
    "949": "done",
    "946": "done",
    "1212": "done",
    "251": "done",
    "1367": "done",
    "1372": "done",
    "1390": "done",
    "1365": "done",
    "966": "done",
    "1035": "done",
    "401": "done",
    "365": "done",
    "414": "done",
    "418": "done",
    "814": "done"
  },
  "prs": {
    "1406": "closed",
    "1408": "open",
    "1413": "open",
    "1420": "open",
    "1431": "open",
    "1432": "open",
    "1435": "open",
    "1437": "open",
    "1438": "closed",
    "1442": "closed",
    "1443": "issue-not-pr",
    "1444": "open",
    "1426": "merged",
    "1429": "closed",
    "1439": "merged",
    "1454": "open",
    "1455": "open",
    "1456": "merged",
    "1457": "merged",
    "1460": "open",
    "1461": "open",
    "1462": "open",
    "1463": "open",
    "1464": "open",
    "1465": "open"
  },
  "monthly": "apr2026_1433",
  "prev_monthly_closed": "1403",
  "notes": "PRs #1426,#1439,#1456,#1457 MERGED. PRs #1429,#1438 CLOSED. #1406 CLOSED. Monthly #1403 closed, April 2026 monthly #1433 active. PR #1431=CMI p-value fix. PR #1432=Delta method CI (closes #336). PR #1435=EconML categorical EM fix. PR #1454=fix NaN p-value when std=0. PR #1455=fix KeyError conditional_MI. PR #1460=fix categorical groupby KeyError + FutureWarning in dummy_outcome_refuter (closes #1316). PR #1461=fix estimate_effect_naive list-form treatment_variable (closes #416). PR #1462=fix TwoStageRegression preinstantiated second_stage_model (closes #1335). PR #1463=remove deprecated copy=False from pandas astype(). PR #1464=feat auto-select default method_name in estimate_effect (closes #365). PR #1465=fix exact_match_cols bugs in DistanceMatchingEstimator + 12 new tests (closes #814). #1444 can be closed (absorbed into #1432). #1443 is ISSUE (CI workflow file protected). Commented #814 (3 bugs in exact_match_cols, fix PR submitted).",
  "fix_attempts": [
    {
      "issue": 814,
      "branch": "repo-assist/fix-issue-814-distance-matching-exact-match",
      "pr": 1465,
      "description": "Fix 3 bugs in DistanceMatchingEstimator.estimate_effect with exact_match_cols; add 12 tests",
      "status": "open",
      "run": "24605278712"
    },
    {
      "issue": 365,
      "branch": "repo-assist/feature-365-smart-method-defaults-20260418",
      "pr": 1464,
      "description": "Auto-select default estimation method when method_name=None",
      "status": "open",
      "run": "24593293212"
    },
    {
      "issue": 1335,
      "branch": "repo-assist/fix-issue-1335-twostage-preinstantiated-estimand",
      "pr": 1462,
      "description": "Fix TwoStageRegressionEstimator pre-instantiated second_stage_model KeyError",
      "status": "open",
      "run": "24566545859"
    }
  ]
}
