{
  "last_run": "2026-05-01T00:00:00Z",
  "last_run_id": "25197668999",
  "comments_made": {
    "517": "2026-05-01T00:00:00Z"
  },
  "monthly": {
    "issue_number": null,
    "month": "2026-05",
    "note": "April #1433 closed this run. May 2026-05 issue created (exact number TBD - search for [Repo Assist] Monthly Activity 2026-05 to find it)"
  },
  "prs": {
    "1464": "open",
    "1465": "open",
    "1466": "open",
    "1467": "open",
    "1468": "open",
    "1472": "open",
    "1475": "open",
    "1477": "open",
    "1479": "open",
    "1481": "open",
    "1482": "open",
    "1483": "open-duplicate",
    "1484": "open",
    "1485": "open",
    "1486": "open",
    "1487": "open",
    "1488": "open",
    "1489": "open",
    "1490": "open",
    "1491": {
      "issue": 801,
      "branch": "repo-assist/fix-issue-801-econml-x-none-error-message",
      "desc": "Improve EconML X=None error message",
      "created": "2026-04-30T13:28:00Z",
      "status": "open"
    },
    "1408": "open",
    "1413": "open",
    "1431": "open",
    "1432": "open",
    "1435": "open",
    "1437": "open",
    "1455": "open",
    "1460": "open",
    "1461": "open-superseded",
    "1462": "open",
    "1470": "open-superseded"
  }
}
